{
  "Utility": {
    "AmmoType": "Rifle",
    "ShotType": "Projectile",
    "ShotSpeed": "60 m/s",
    "NoiseLevel": "Alarming",
    "FireRate": "6",
    "Accuracy": "18.2",
    "Magazine": "45",
    "MaxAmmo": "540",
    "Reload": "2 s",
    "Disposition": "●●●●● (1.55x)"
  },
  "Normal": {
    "Attack1Total": "50 (75%)",
    "Attack1ShotType": "Projectile",
    "Attack1ShotSpeed": "60 m/s",
    "Attack1FireRate": "6",
    "Attack1Accuracy": "18.2",
    "Attack1BurstCount": "3",
    "Attack1BurstFireRate": "5",
    "Attack1BurstDelay": "0.1 s",
    "Attack1Multishot": "1 (50 damage per projectile)",
    "Attack1StatusChance": "17%",
    "Attack1CritChance": "20%",
    "Attack1CritMultiplier": "2.3x"
  },
  "Harpoon": {
    "Attack2Total": "100 (50%)",
    "Attack2ShotType": "Projectile",
    "Attack2ShotSpeed": "50 m/s",
    "ForcedProcs": "Puncture Damage Puncture",
    "Attack2Range": "40 m",
    "Attack2FireRate": "1.5",
    "Attack2Accuracy": "100",
    "Attack2Multishot": "1 (100 damage per projectile)",
    "Attack2StatusChance": "13%",
    "Attack2CritChance": "25%",
    "Attack2CritMultiplier": "2.3x"
  },
  "Miscellaneous": {
    "ExilusPolarity": "",
    "Polarities": "",
    "Users": "Drekar Elite LancerDraga",
    "Introduced": "Update 17.0 (2015-07-31)",
    "InternalName": "/Lotus/Weapons/Grineer/LongGuns/GrnHarpoonGun/GrnHarpoonGun"
  }
}